tests/__init__.py
tests/test_connection.py
tests/test_libero.py
vlagents/__init__.py
vlagents/__main__.py
vlagents/client.py
vlagents/evaluator_envs.py
vlagents/policies.py
vlagents/server.py
vlagents/wrappers.py
vlagents-0.1.0.dist-info/licenses/LICENSE
vlagents-0.1.0.dist-info/METADATA
vlagents-0.1.0.dist-info/WHEEL
vlagents-0.1.0.dist-info/top_level.txt
vlagents-0.1.0.dist-info/RECORD
