Metadata-Version: 2.4
Name: vlagents
Version: 0.1.0
Summary: Modular VLA and Environment interfaces.
Author-email: Tobias Jülg <tobias.juelg@utn.de>
Maintainer-email: Tobias Jülg <tobias.juelg@utn.de>
License-Expression: Apache-2.0
Project-URL: Homepage, https://github.com/RobotControlStack/vlagents
Project-URL: Issues, https://github.com/RobotControlStack/vlagents/issues
Classifier: Programming Language :: Python :: 3
Requires-Python: >=3.10
License-File: LICENSE
Requires-Dist: rpyc
Requires-Dist: numpy
Requires-Dist: json_numpy
Requires-Dist: gymnasium
Requires-Dist: typer
Requires-Dist: simple-slurm
Requires-Dist: wandb
Requires-Dist: pillow
Requires-Dist: tqdm
Requires-Dist: simplejpeg
Provides-Extra: dev
Requires-Dist: ruff; extra == "dev"
Requires-Dist: black; extra == "dev"
Requires-Dist: isort; extra == "dev"
Requires-Dist: mypy; extra == "dev"
Requires-Dist: build; extra == "dev"
Requires-Dist: pytest; extra == "dev"
Requires-Dist: commitizen; extra == "dev"
Dynamic: license-file
